ConvenTools
