Metadata-Version: 1.0
Name: ConvenTools
Version: 0.0.9
Summary: This is a python toolbox，It is mainly used for database operation and excel operation
Home-page: https://www.github.com/lueans
Author: lueans
Author-email: 2427770136@qq.com
License: UNKNOWN
Platform: UNKNOWN
